{
  "accordion": {
    "default": {
      "border": {
        "background": {
          "value": "{background.interactive.transparent}",
          "type": "color"
        },
        "color": {
          "value": "{border.primary}",
          "type": "color"
        }
      },
      "border-width": {
        "value": {
          "width": "{border-width.interactive.xs}"
        },
        "type": "border"
      },
      "icon-color": {
        "value": "{icon.primary}",
        "type": "color"
      },
      "label-color": {
        "value": "{text.primary}",
        "type": "color"
      },
      "borderless": {
        "border-width": {
          "value": {
            "width": "{border-width.interactive.none}"
          },
          "type": "border"
        }
      },
      "border-radius": {
        "value": "{radius.element.md}",
        "type": "borderRadius"
      }
    },
    "focus-active": {
      "border": {
        "background": {
          "value": "{background.interactive.transparent}",
          "type": "color"
        }
      }
    },
    "focus": {
      "border-width": {
        "value": {
          "width": "{border-width.outline.sm}"
        },
        "type": "border"
      },
      "borderless": {
        "border-width": {
          "value": {
            "width": "{border-width.interactive.none}"
          },
          "type": "border"
        }
      },
      "border-color": {
        "value": "{outline.focus}",
        "type": "color"
      },
      "border-radius": {
        "value": "{radius.layout.md}",
        "type": "borderRadius"
      }
    },
    "hover": {
      "border-width": {
        "value": {
          "width": "{border-width.interactive.xs}"
        },
        "type": "border"
      },
      "icon": {
        "color": {
          "value": "{icon.primary}",
          "type": "color"
        }
      },
      "background": {
        "value": "{background.surface.hover}",
        "type": "color"
      }
    },
    "icon": {
      "color": {
        "value": "{icon.primary}",
        "type": "color"
      }
    },
    "title": {
      "font": {
        "family": {
          "value": "text.family.heading",
          "type": "fontFamily"
        },
        "size": {
          "value": "text.size.heading.h3",
          "type": "fontSize"
        },
        "weight": {
          "value": "text.weight.heading",
          "type": "fontWeight"
        }
      },
      "line-height": {
        "value": "text.line-height.heading.h3",
        "type": "lineHeight"
      }
    },
    "content": {
      "font": {
        "family": {
          "value": "text.family.label",
          "type": "fontFamily"
        },
        "weight": {
          "value": "text.weight.label.secondary",
          "type": "fontWeight"
        }
      },
      "size": {
        "value": "text.size.label.sm",
        "type": "fontSize"
      },
      "line-height": {
        "value": "text.line-height.label.sm",
        "type": "lineHeight"
      }
    }
  }
}